README.md
setup.py
pader/__init__.py
pader.egg-info/PKG-INFO
pader.egg-info/SOURCES.txt
pader.egg-info/dependency_links.txt
pader.egg-info/not-zip-safe
pader.egg-info/requires.txt
pader.egg-info/top_level.txt
pader/core/__init__.py
pader/core/exceptions.py
pader/core/request.py
pader/core/response.py
pader/core/queue/__init__.py
pader/core/queue/request_queue.py
pader/core/spiders/__init__.py
pader/core/spiders/base_spider.py
pader/core/spiders/pader_spider.py
pader/core/spiders/slow_spider.py