Metadata-Version: 2.1
Name: pader
Version: 0.2
Summary: 轻量框架，支持中间件、检验等功能
Home-page: https://github.com/markadc/sqlman
Author: WangTuo
Author-email: markadc@126.com
License: MIT
Keywords: Python,Spider
